namex/__init__.py
namex/convert.py
namex/export.py
namex/generate.py
namex-0.0.8.dist-info/LICENSE
namex-0.0.8.dist-info/METADATA
namex-0.0.8.dist-info/WHEEL
namex-0.0.8.dist-info/top_level.txt
namex-0.0.8.dist-info/RECORD
